.DS_Store
keliya_lib/__init__.py
keliya_lib/db_handler.py
keliya_lib/log_handler.py
keliya_lib/permission_handler.py
keliya_lib/user_handler.py
keliya_lib-0.3.4.dist-info/METADATA
keliya_lib-0.3.4.dist-info/WHEEL
keliya_lib-0.3.4.dist-info/top_level.txt
keliya_lib-0.3.4.dist-info/RECORD
