Metadata-Version: 2.2
Name: keliya_lib
Version: 0.3.4
Summary: AWS Lambda helpers
Author: Erandra Jayasundara
Author-email: erandraj@gmail.com
License: MIT
Requires-Dist: requests
Requires-Dist: boto3
Dynamic: author
Dynamic: author-email
Dynamic: description
Dynamic: description-content-type
Dynamic: license
Dynamic: requires-dist
Dynamic: summary
